{
  "collection": "trotskyists",
  "thinker": "Walter Held",
  "slug": "walter-held",
  "source_url": "https://www.marxists.org/archive/held-walter/index.htm",
  "status": "success",
  "message": "Collected 15 candidate works.",
  "warnings": [],
  "works": [
    {
      "title": "Heckert ‘Explains’ the Debacle",
      "url": "https://www.marxists.org/archive/held-walter/1933/xx/heckert.html"
    },
    {
      "title": "Int’l Youth Bureau Collapses",
      "url": "https://www.marxists.org/archive/held-walter/1935/10/iyb.htm"
    },
    {
      "title": "Once Again Lenin and Luxemburg",
      "url": "https://www.marxists.org/archive/held-walter/1940/06/lenlux.htm"
    },
    {
      "title": "Stalin in Reality and Legend",
      "url": "https://www.marxists.org/archive/held-walter/1935/12/stalin.htm"
    },
    {
      "title": "Stalinism and the POUM in the Spanish Revolution",
      "url": "https://www.marxists.org/archive/held-walter/1937/03/spain.htm"
    },
    {
      "title": "Stalinist Diplomacy Leaves Trail of Treachery for International Proletariat",
      "url": "https://www.marxists.org/archive/held-walter/1933/xx/staldip.htm"
    },
    {
      "title": "The Copenhagen Socialist Youth Conference",
      "url": "https://www.marxists.org/archive/held-walter/1935/10/syi.htm"
    },
    {
      "title": "The Course of Herr Brandler",
      "url": "https://www.marxists.org/archive/held-walter/1938/04/brandler.htm"
    },
    {
      "title": "The Defense of Czechoslovakia",
      "url": "https://www.marxists.org/archive/held-walter/1938/10/czechoslovakia.htm"
    },
    {
      "title": "The Designs Behind the Four Power Pact",
      "url": "https://www.marxists.org/archive/held-walter/1933/xx/4powerpact.htm"
    },
    {
      "title": "The End of Locarno",
      "url": "https://www.marxists.org/archive/held-walter/1936/06/locarno.htm"
    },
    {
      "title": "The German Left and Bolshevism",
      "url": "https://www.marxists.org/archive/held-walter/1939/02/germleft.html"
    },
    {
      "title": "The People’s Front in France",
      "url": "https://www.marxists.org/archive/held-walter/1936/04/peoplesfront.htm"
    },
    {
      "title": "Why The German Revolution Failed",
      "url": "https://www.marxists.org/archive/held-walter/1942/12/germrev.htm"
    },
    {
      "title": "Will the Soviet Union Join the League of Nations?",
      "url": "https://www.marxists.org/archive/held-walter/1934/06/su-league.htm"
    }
  ],
  "visited_urls": [
    "https://www.marxists.org/archive/held-walter/index.htm"
  ]
}
