{
  "n": "Cheddi Jagan",
  "c": "National Liberation",
  "d": "Marxist thinker and theorist in the tradition of national liberation.",
  "b": "https://www.marxists.org/reference/archive/",
  "i": "https://upload.wikimedia.org/wikipedia/commons/1/11/Behar_Herald_15-07-2019.pdf",
  "t": "https://upload.wikimedia.org/wikipedia/commons/thumb/1/11/Behar_Herald_15-07-2019.pdf/page1-200px-Behar_Herald_15-07-2019.pdf.jpg",
  "w": 10,
  "subjects": [
    {
      "name": "Letters",
      "count": 1
    },
    {
      "name": "General",
      "count": 3
    },
    {
      "name": "History",
      "count": 4
    },
    {
      "name": "Criticism",
      "count": 1
    },
    {
      "name": "Political Theory",
      "count": 1
    }
  ],
  "s": "cheddi jagan national liberation marxist thinker and theorist in the tradition of national liberation. letters general history criticism political theory"
}
