[
  {
    "name": "Karl Marx",
    "category": "Founders",
    "description": "German philosopher, economist, and revolutionary socialist. Co-founder of Marxism and author of Das Kapital and the Communist Manifesto. Developed the theory of historical materialism and critique of political economy.",
    "bioUrl": "/reference/archive/marx/bio/index.htm",
    "works": [
      {
        "title": "Das Kapital",
        "url": "/archive/marx/works/1867-c1/"
      },
      {
        "title": "Communist Manifesto",
        "url": "/archive/marx/works/1848/communist-manifesto/"
      },
      {
        "title": "The German Ideology",
        "url": "/archive/marx/works/1845/german-ideology/"
      },
      {
        "title": "The Eighteenth Brumaire of Louis Bonaparte",
        "url": "/archive/marx/works/1852/18th-brumaire/"
      },
      {
        "title": "The Poverty of Philosophy",
        "url": "/archive/marx/works/1847/poverty-philosophy/"
      },
      {
        "title": "Grundrisse",
        "url": "/archive/marx/works/1857/grundrisse/"
      }
    ],
    "imageUrl": "https://upload.wikimedia.org/wikipedia/commons/b/b3/Karl_Marx_by_John_Jabez_Edwin_Mayall_1875_-_Restored.png"
  },
  {
    "name": "Friedrich Engels",
    "category": "Founders",
    "description": "German philosopher, social scientist, journalist, and businessman. Co-founder of Marxism with Karl Marx. Best known for his contributions to revolutionary theory and his support of the working-class movement.",
    "bioUrl": "/reference/archive/engels/bio/index.htm",
    "works": [
      {
        "title": "Anti-Dühring",
        "url": "/archive/marx/works/1877/anti-duhring/"
      },
      {
        "title": "The Origin of the Family",
        "url": "/archive/marx/works/1884/origin-family/"
      },
      {
        "title": "Socialism: Utopian and Scientific",
        "url": "/archive/marx/works/1880/soc-utop/index.htm"
      },
      {
        "title": "The Condition of the Working Class in England",
        "url": "/archive/marx/works/1845/condition-working-class/"
      },
      {
        "title": "The Peasant War in Germany",
        "url": "/archive/marx/works/1850/peasant-war-germany/"
      }
    ],
    "imageUrl": "https://upload.wikimedia.org/wikipedia/commons/2/21/Friedrich_Engels_portrait_%28cropped%29.jpg"
  },
  {
    "name": "Vladimir Lenin",
    "category": "Bolsheviks",
    "description": "Russian revolutionary, politician, and political theorist. Leader of the Bolshevik Party and the October Revolution of 1917. Founded the Soviet Union and developed Leninism as a variant of Marxism.",
    "bioUrl": "/reference/archive/lenin/bio/index.htm",
    "works": [
      {
        "title": "What Is To Be Done?",
        "url": "/archive/lenin/works/1901/witbd/"
      },
      {
        "title": "Imperialism, the Highest Stage of Capitalism",
        "url": "/archive/lenin/works/1916/imp-hsc/"
      },
      {
        "title": "State and Revolution",
        "url": "/archive/lenin/works/1917/staterev/"
      },
      {
        "title": "April Theses",
        "url": "/archive/lenin/works/1917/apr03.htm"
      },
      {
        "title": "Materialism and Empirio-Criticism",
        "url": "/archive/lenin/works/1908/mec/"
      },
      {
        "title": "Left-Wing Communism: An Infantile Disorder",
        "url": "/archive/lenin/works/1920/lwc/"
      }
    ],
    "imageUrl": "https://upload.wikimedia.org/wikipedia/commons/1/1f/Vladimir_Lenin_in_July_1920_by_Pavel_Zhukov.jpg"
  },
  {
    "name": "Leon Trotsky",
    "category": "Bolsheviks",
    "description": "Russian revolutionary, Marxist theorist, and Soviet politician. Key organizer of the October Revolution and founder of the Red Army. Later exiled and assassinated for opposing Stalinism.",
    "bioUrl": "/reference/archive/trotsky/bio/index.htm",
    "works": [
      {
        "title": "The Permanent Revolution",
        "url": "/archive/trotsky/1931/tpr/"
      },
      {
        "title": "History of the Russian Revolution",
        "url": "/archive/trotsky/1930/hrr/"
      },
      {
        "title": "The Revolution Betrayed",
        "url": "/archive/trotsky/1936/revbet/"
      },
      {
        "title": "My Life",
        "url": "/archive/trotsky/1930/mylife/"
      },
      {
        "title": "The Transitional Program",
        "url": "/archive/trotsky/1938/tp/"
      },
      {
        "title": "Their Morals and Ours",
        "url": "/archive/trotsky/1938/morals.htm"
      }
    ],
    "imageUrl": "https://upload.wikimedia.org/wikipedia/commons/3/31/Leon_trotsky.jpg"
  },
  {
    "name": "Rosa Luxemburg",
    "category": "Social Democracy",
    "description": "Polish Marxist theorist, philosopher, economist, and revolutionary socialist. Co-founder of the Spartacus League and the Communist Party of Germany. Theorized imperialism and mass strikes.",
    "bioUrl": "/reference/archive/luxemburg/index.htm",
    "works": [
      {
        "title": "Reform or Revolution",
        "url": "/archive/luxemburg/1900/reform-revolution/"
      },
      {
        "title": "The Accumulation of Capital",
        "url": "/archive/luxemburg/1913/accumulation-capital/"
      },
      {
        "title": "The Mass Strike",
        "url": "/archive/luxemburg/1906/mass-strike/"
      },
      {
        "title": "The Russian Revolution",
        "url": "/archive/luxemburg/1918/russian-revolution/"
      },
      {
        "title": "The Junius Pamphlet",
        "url": "/archive/luxemburg/1915/junius/"
      }
    ],
    "imageUrl": "https://upload.wikimedia.org/wikipedia/commons/5/52/Rosa_Luxemburg.jpg"
  },
  {
    "name": "Antonio Gramsci",
    "category": "Italian Communists",
    "description": "Italian Marxist philosopher, journalist, linguist, writer, and political theorist. Founder of the Italian Communist Party. Developed concepts of cultural hegemony and the role of intellectuals.",
    "bioUrl": "/reference/archive/gramsci/bio/index.htm",
    "works": [
      {
        "title": "Prison Notebooks",
        "url": "/archive/gramsci/"
      },
      {
        "title": "The Southern Question",
        "url": "/archive/gramsci/"
      },
      {
        "title": "Selections from Political Writings",
        "url": "/archive/gramsci/"
      }
    ],
    "imageUrl": "https://upload.wikimedia.org/wikipedia/commons/4/4b/Antonio_Gramsci_1920.jpg"
  },
  {
    "name": "Karl Kautsky",
    "category": "Social Democracy",
    "description": "Czech-Austrian philosopher, journalist, and Marxist theorist. Leading theoretician of the Social Democratic Party of Germany. Popularized Marxist economics and opposed Bolshevism.",
    "bioUrl": "/reference/archive/kautsky/bio/index.htm",
    "works": [
      {
        "title": "The Economic Doctrines of Karl Marx",
        "url": "/archive/kautsky/1883/econ/index.htm"
      },
      {
        "title": "The Road to Power",
        "url": "/archive/kautsky/1909/power/index.htm"
      },
      {
        "title": "The Dictatorship of the Proletariat",
        "url": "/archive/kautsky/1918/dictprole/"
      },
      {
        "title": "Terrorism and Communism",
        "url": "/archive/kautsky/1919/terrcomm/"
      }
    ],
    "imageUrl": "https://upload.wikimedia.org/wikipedia/commons/thumb/a/ae/Karl_Kautsky.jpg/800px-Karl_Kautsky.jpg"
  },
  {
    "name": "Georgi Plekhanov",
    "category": "Social Democracy",
    "description": "Russian revolutionary theorist, philosopher and Marxist theorist. Father of Russian Marxism. Founded the first Russian Marxist organization, the Emancipation of Labour.",
    "bioUrl": "/reference/archive/plekhanov/bio/index.htm",
    "works": [
      {
        "title": "The Development of the Monist View of History",
        "url": "/archive/plekhanov/"
      },
      {
        "title": "Fundamental Problems of Marxism",
        "url": "/archive/plekhanov/"
      }
    ],
    "imageUrl": "https://upload.wikimedia.org/wikipedia/commons/thumb/4/4e/Georgi_Plekhanov_c._1901.jpg/800px-Georgi_Plekhanov_c._1901.jpg"
  },
  {
    "name": "Georg Lukacs",
    "category": "Western Marxism",
    "description": "Hungarian Marxist philosopher, aesthetician, literary historian, and critic. One of the founders of Western Marxism. Best known for his theory of reification and concept of class consciousness.",
    "bioUrl": "/reference/archive/lukacs/index.htm",
    "works": [
      {
        "title": "History and Class Consciousness",
        "url": "/archive/lukacs/"
      },
      {
        "title": "The Destruction of Reason",
        "url": "/archive/lukacs/"
      },
      {
        "title": "The Theory of the Novel",
        "url": "/archive/lukacs/"
      }
    ],
    "imageUrl": "https://upload.wikimedia.org/wikipedia/commons/thumb/4/4e/Gy%C3%B6rgy_Luk%C3%A1cs_1952.jpg/800px-Gy%C3%B6rgy_Luk%C3%A1cs_1952.jpg"
  },
  {
    "name": "Louis Althusser",
    "category": "French Left",
    "description": "French Marxist philosopher. Developed the theory of structural Marxism and made major contributions to debates on ideological state apparatuses, overdetermination, and the epistemological break in Marx's thought.",
    "bioUrl": "/reference/archive/althusser/bio/index.htm",
    "works": [
      {
        "title": "For Marx",
        "url": "/archive/althusser/"
      },
      {
        "title": "Reading Capital",
        "url": "/archive/althusser/"
      },
      {
        "title": "Ideology and Ideological State Apparatuses",
        "url": "/archive/althusser/"
      },
      {
        "title": "On the Reproduction of Capitalism",
        "url": "/archive/althusser/"
      }
    ],
    "imageUrl": "https://upload.wikimedia.org/wikipedia/commons/thumb/0/0d/Louis_Althusser_1970.jpg/800px-Louis_Althusser_1970.jpg"
  },
  {
    "name": "Jean-Paul Sartre",
    "category": "French Left",
    "description": "French existentialist philosopher, playwright, novelist, screenwriter, political activist, biographer, and literary critic. Combined existentialism with Marxism and wrote extensively on freedom and responsibility.",
    "bioUrl": "/reference/archive/sartre/bio/index.htm",
    "works": [
      {
        "title": "Being and Nothingness",
        "url": "/archive/sartre/"
      },
      {
        "title": "Critique of Dialectical Reason",
        "url": "/archive/sartre/"
      },
      {
        "title": "The Words",
        "url": "/archive/sartre/"
      },
      {
        "title": "Existentialism is a Humanism",
        "url": "/archive/sartre/"
      }
    ],
    "imageUrl": "https://upload.wikimedia.org/wikipedia/commons/thumb/2/2b/JP_Sartre_1967_crop.jpg/800px-JP_Sartre_1967_crop.jpg"
  },
  {
    "name": "Herbert Marcuse",
    "category": "Frankfurt School",
    "description": "German-American philosopher, sociologist, and political theorist associated with the Frankfurt School. Developed critical theory and was a major influence on the New Left movements of the 1960s.",
    "bioUrl": "/reference/archive/marcuse/index.htm",
    "works": [
      {
        "title": "One-Dimensional Man",
        "url": "/reference/archive/marcuse/"
      },
      {
        "title": "Eros and Civilization",
        "url": "/reference/archive/marcuse/"
      },
      {
        "title": "Reason and Revolution",
        "url": "/reference/archive/marcuse/"
      },
      {
        "title": "An Essay on Liberation",
        "url": "/reference/archive/marcuse/"
      }
    ],
    "imageUrl": "https://upload.wikimedia.org/wikipedia/commons/thumb/5/5e/Herbert_Marcuse_1965.jpg/800px-Herbert_Marcuse_1965.jpg"
  },
  {
    "name": "Theodor Adorno",
    "category": "Frankfurt School",
    "description": "German philosopher, sociologist, psychologist, musicologist, and composer. Co-founder of the Frankfurt School. Developed critical theory and wrote extensively on culture, music, and aesthetics.",
    "bioUrl": "/reference/archive/adorno/bio/index.htm",
    "works": [
      {
        "title": "Dialectic of Enlightenment",
        "url": "/reference/archive/adorno/"
      },
      {
        "title": "Negative Dialectics",
        "url": "/reference/archive/adorno/"
      },
      {
        "title": "Minima Moralia",
        "url": "/reference/archive/adorno/"
      },
      {
        "title": "The Culture Industry",
        "url": "/reference/archive/adorno/"
      }
    ],
    "imageUrl": "https://upload.wikimedia.org/wikipedia/commons/thumb/9/93/Theodor_W._Adorno_1964_cropped_and_colorized.jpg/800px-Theodor_W._Adorno_1964_cropped_and_colorized.jpg"
  },
  {
    "name": "Walter Benjamin",
    "category": "Frankfurt School",
    "description": "German Jewish philosopher, cultural critic and essayist. Associated with the Frankfurt School. Wrote on art, literature, history, and modernity. Influential in aesthetic and Marxist theory.",
    "bioUrl": "/reference/archive/benjamin/bio/index.htm",
    "works": [
      {
        "title": "The Work of Art in the Age of Mechanical Reproduction",
        "url": "/reference/archive/benjamin/"
      },
      {
        "title": "Theses on the Philosophy of History",
        "url": "/reference/archive/benjamin/"
      },
      {
        "title": "Illuminations",
        "url": "/reference/archive/benjamin/"
      },
      {
        "title": "The Arcades Project",
        "url": "/reference/archive/benjamin/"
      }
    ],
    "imageUrl": "https://upload.wikimedia.org/wikipedia/commons/c/cc/Walter_Benjamin_vers_1928.jpg"
  },
  {
    "name": "Che Guevara",
    "category": "Guerilla Marxism",
    "description": "Argentine Marxist revolutionary, physician, author, guerrilla leader, diplomat, and military theorist. A major figure of the Cuban Revolution. Icon of leftist revolutionary movements.",
    "bioUrl": "/archive/guevara/index.htm",
    "works": [
      {
        "title": "Guerrilla Warfare",
        "url": "/archive/guevara/"
      },
      {
        "title": "Socialism and Man in Cuba",
        "url": "/archive/guevara/"
      },
      {
        "title": "The Motorcycle Diaries",
        "url": "/archive/guevara/"
      },
      {
        "title": "Man and Socialism in Cuba",
        "url": "/archive/guevara/"
      }
    ],
    "imageUrl": "https://upload.wikimedia.org/wikipedia/commons/thumb/6/6a/Che_Guevara_Gerardo_S%C3%A1nchez_Noguera.jpg/800px-Che_Guevara_Gerardo_S%C3%A1nchez_Noguera.jpg"
  },
  {
    "name": "Fidel Castro",
    "category": "National Liberation",
    "description": "Cuban revolutionary and politician who served as the Prime Minister of Cuba and President of Cuba. Led the Cuban Revolution and established the first communist state in the Western Hemisphere.",
    "bioUrl": "/archive/castro/index.htm",
    "works": [
      {
        "title": "History Will Absolve Me",
        "url": "/archive/castro/"
      },
      {
        "title": "My Life",
        "url": "/archive/castro/"
      },
      {
        "title": "Selected Speeches and Writings",
        "url": "/archive/castro/"
      }
    ],
    "imageUrl": "https://upload.wikimedia.org/wikipedia/commons/thumb/8/8b/Fidel_Castro_1977.jpg/800px-Fidel_Castro_1977.jpg"
  },
  {
    "name": "Ho Chi Minh",
    "category": "National Liberation",
    "description": "Vietnamese revolutionary and politician. President of North Vietnam and founder of the Democratic Republic of Vietnam. Led the Vietnamese independence movement against French colonial rule.",
    "bioUrl": "/archive/ho/index.htm",
    "works": [
      {
        "title": "Selected Works",
        "url": "/archive/ho/"
      },
      {
        "title": "Prison Diary",
        "url": "/archive/ho/"
      },
      {
        "title": "Path Which Led Me to Leninism",
        "url": "/archive/ho/"
      }
    ],
    "imageUrl": "https://upload.wikimedia.org/wikipedia/commons/4/43/Nguyen_A%C3%AFn_Nu%C3%A4%27C_%28Ho-Chi-Minh%29%2C_d%C3%A9l%C3%A9gu%C3%A9_indochinois%2C_Congr%C3%A8s_communiste_de_Marseille%2C_1921%2C_Meurisse%2C_BNF_Gallica.jpg"
  },
  {
    "name": "Frantz Fanon",
    "category": "National Liberation",
    "description": "Martiniquais psychiatrist, philosopher, radical pan-Africanist and humanist. Theorized the psychology of colonialism and the role of violence in decolonization. Influential in post-colonial studies.",
    "bioUrl": "/reference/archive/fanon/bio/index.htm",
    "works": [
      {
        "title": "The Wretched of the Earth",
        "url": "/archive/fanon/"
      },
      {
        "title": "Black Skin, White Masks",
        "url": "/archive/fanon/"
      },
      {
        "title": "A Dying Colonialism",
        "url": "/archive/fanon/"
      },
      {
        "title": "Toward the African Revolution",
        "url": "/archive/fanon/"
      }
    ],
    "imageUrl": "https://upload.wikimedia.org/wikipedia/commons/thumb/4/4e/Frantz_Fanon_in_1950s.jpg/800px-Frantz_Fanon_in_1950s.jpg"
  },
  {
    "name": "Angela Davis",
    "category": "Black Liberation",
    "description": "American political activist, philosopher, academic, and author. Member of the Communist Party USA. Works on feminism, class, gender, and the abolition of prisons. Icon of the black power movement.",
    "bioUrl": "/archive/davis-angela/index.htm",
    "works": [
      {
        "title": "Women, Race and Class",
        "url": "/archive/davis-angela/"
      },
      {
        "title": "Are Prisons Obsolete?",
        "url": "/archive/davis-angela/"
      },
      {
        "title": "The Angela Davis Reader",
        "url": "/archive/davis-angela/"
      }
    ],
    "imageUrl": "https://upload.wikimedia.org/wikipedia/commons/thumb/4/4e/Angela_Davis_2010.jpg/800px-Angela_Davis_2010.jpg"
  },
  {
    "name": "Malcolm X",
    "category": "Black Liberation",
    "description": "African American civil rights leader, minister, and human rights activist. Prominent figure in the Nation of Islam and later Sunni Islam. Advocated black empowerment and Pan-Africanism.",
    "bioUrl": "/archive/malcolm-x/index.htm",
    "works": [
      {
        "title": "The Autobiography of Malcolm X",
        "url": "/archive/malcolm-x/"
      },
      {
        "title": "Malcolm X Speaks",
        "url": "/archive/malcolm-x/"
      }
    ],
    "imageUrl": "https://upload.wikimedia.org/wikipedia/commons/thumb/0/05/Malcolm_X_NYWTS_2a.jpg/800px-Malcolm_X_NYWTS_2a.jpg"
  },
  {
    "name": "Mao Zedong",
    "category": "Maoists",
    "description": "Chinese communist revolutionary, political theorist, and founding father of the People's Republic of China. Chairman of the Chinese Communist Party. Developed Maoism, a variant of Marxism-Leninism.",
    "bioUrl": "/reference/archive/mao/bio/index.htm",
    "works": [
      {
        "title": "On Contradiction",
        "url": "/reference/archive/mao/selected-works/"
      },
      {
        "title": "On Practice",
        "url": "/reference/archive/mao/selected-works/"
      },
      {
        "title": "Quotations from Chairman Mao",
        "url": "/reference/archive/mao/selected-works/"
      },
      {
        "title": "On Guerrilla Warfare",
        "url": "/reference/archive/mao/selected-works/"
      }
    ],
    "imageUrl": "https://upload.wikimedia.org/wikipedia/commons/thumb/5/56/Mao_Zedong_1945.jpg/800px-Mao_Zedong_1945.jpg"
  },
  {
    "name": "Alexandra Kollontai",
    "category": "Feminists",
    "description": "Russian revolutionary, diplomat, and Bolshevik government official. The most prominent woman in the Soviet administration. Developed Marxist feminism and argued for sexual and reproductive freedom.",
    "bioUrl": "/archive/kollontai/index.htm",
    "works": [
      {
        "title": "The Autobiography of a Sexually Emancipated Communist Woman",
        "url": "/archive/kollontai/"
      },
      {
        "title": "Selected Articles and Speeches",
        "url": "/archive/kollontai/"
      },
      {
        "title": "Communism and the Family",
        "url": "/archive/kollontai/"
      }
    ],
    "imageUrl": "https://upload.wikimedia.org/wikipedia/commons/thumb/6/68/Alexandra_Kollontai.jpg/800px-Alexandra_Kollontai.jpg"
  },
  {
    "name": "Simone de Beauvoir",
    "category": "Feminists",
    "description": "French existentialist philosopher, writer, social theorist, and feminist activist. Wrote on existentialism, ethics, and feminism. Author of The Second Sex, a foundational text of feminist philosophy.",
    "bioUrl": "/reference/archive/debeauvoir/bio/index.htm",
    "works": [
      {
        "title": "The Second Sex",
        "url": "/reference/archive/debeauvoir/"
      },
      {
        "title": "The Ethics of Ambiguity",
        "url": "/reference/archive/debeauvoir/"
      },
      {
        "title": "The Mandarins",
        "url": "/reference/archive/debeauvoir/"
      }
    ],
    "imageUrl": "https://upload.wikimedia.org/wikipedia/commons/thumb/a/a6/Simone_de_Beauvoir_1967.jpg/800px-Simone_de_Beauvoir_1967.jpg"
  }
]