{
  "n": "Ludwig Feuerbach",
  "c": "Philosophy",
  "d": "Marxist thinker and theorist in the tradition of philosophy.",
  "b": "https://www.marxists.org/reference/archive/",
  "i": "https://upload.wikimedia.org/wikipedia/commons/e/eb/Feuerbach_Ludwig_retouched.jpg",
  "t": "https://upload.wikimedia.org/wikipedia/commons/thumb/e/eb/Feuerbach_Ludwig_retouched.jpg/250px-Feuerbach_Ludwig_retouched.jpg",
  "w": 0,
  "s": "ludwig feuerbach philosophy marxist thinker and theorist in the tradition of philosophy."
}
