[
  {
    "title": "A page has been turned (the formation of the NPA)",
    "url": "https://www.marxists.org/archive/bensaid/2009/02/npa1.htm"
  },
  {
    "title": "Alain Badiou and the Miracle of the Event",
    "url": "https://www.marxists.org/archive/bensaid/2004/xx/badiou.htm"
  },
  {
    "title": "Eight Months of the Left Government in France",
    "url": "https://www.marxists.org/archive/bensaid/1982/01/8months.html"
  },
  {
    "title": "Foundation of the NPA (France)– “We need to create a common culture”",
    "url": "https://www.marxists.org/archive/bensaid/2009/02/npa2.htm"
  },
  {
    "title": "France – From the LCR to the NPA",
    "url": "https://www.marxists.org/archive/bensaid/2008/12/lcr-npa.htm"
  },
  {
    "title": "France: Neo-Liberal Reform and Popular Rebellion",
    "url": "https://www.marxists.org/archive/bensaid/1996/01/neoliberal.htm"
  },
  {
    "title": "France: “The question of a link between workers and students is immediate”",
    "url": "https://www.marxists.org/archive/bensaid/2006/03/work-stud.htm"
  },
  {
    "title": "How left is Left in Europe? New Centre, Third Way",
    "url": "https://www.marxists.org/archive/bensaid/1998/12/howleft.htm"
  },
  {
    "title": "Leninism in the 21st century",
    "url": "https://www.marxists.org/archive/bensaid/2001/11/leninism.htm"
  },
  {
    "title": "Letter to the comrades of the Democracia socialista (DS-PT), Brazil",
    "url": "https://www.marxists.org/archive/bensaid/2005/01/dspt-brazil.htm"
  },
  {
    "title": "Notes on recent developments in the European radical Left",
    "url": "https://www.marxists.org/archive/bensaid/2009/12/europe.htm"
  },
  {
    "title": "On a Recent Book by John Holloway",
    "url": "https://www.marxists.org/archive/bensaid/2005/xx/holloway.htm"
  },
  {
    "title": "On the return of the politico-strategic question",
    "url": "https://www.marxists.org/archive/bensaid/2006/08/polstrat.htm"
  },
  {
    "title": "Operation ‘Bullshit Unlimited’",
    "url": "https://www.marxists.org/archive/bensaid/2002/08/bullshit.htm"
  },
  {
    "title": "Principles flouted – on the PT (Brazil)",
    "url": "https://www.marxists.org/archive/bensaid/2002/09/pt-brazil.htm"
  },
  {
    "title": "Screams and spit",
    "url": "https://www.marxists.org/archive/bensaid/2005/xx/comments.htm"
  },
  {
    "title": "Stalinism and Bolshevism",
    "url": "https://www.marxists.org/archive/bensaid/2005/12/stal-bolsh.htm"
  },
  {
    "title": "The 1976 Lebanese civil war",
    "url": "https://www.marxists.org/archive/bensaid/1982/10/lebanon.html"
  },
  {
    "title": "The Baggage of Exodus",
    "url": "https://www.marxists.org/archive/bensaid/2000/xx/exodus.htm"
  },
  {
    "title": "The French elections and our strategic project",
    "url": "https://www.marxists.org/archive/bensaid/2007/04/election.htm"
  },
  {
    "title": "The Mole and the Locomotive",
    "url": "https://www.marxists.org/archive/bensaid/2001/03/mole.htm"
  },
  {
    "title": "The party and the period",
    "url": "https://www.marxists.org/archive/bensaid/2005/11/party-period.htm"
  },
  {
    "title": "The powers of communism",
    "url": "https://www.marxists.org/archive/bensaid/2009/12/powers.htm"
  },
  {
    "title": "The roots of the crisis",
    "url": "https://www.marxists.org/archive/bensaid/1980/xx/rootscrisis.html"
  },
  {
    "title": "Theses of resistance",
    "url": "https://www.marxists.org/archive/bensaid/2004/12/resist.htm"
  },
  {
    "title": "Thirty years after – A critical introduction to the Marxism of Ernest Mandel",
    "url": "https://www.marxists.org/archive/bensaid/2007/07/mandel.htm"
  },
  {
    "title": "Why our German friends are wrong on EU Constitution",
    "url": "https://www.marxists.org/archive/bensaid/2005/05/eu-const.htm"
  },
  {
    "title": "“It is time to define the strategy”",
    "url": "https://www.marxists.org/archive/bensaid/2009/10/strategy.htm"
  },
  {
    "title": "“Leaps, Leaps, Leaps” – Lenin and Politics",
    "url": "https://www.marxists.org/archive/bensaid/2002/07/leaps.htm"
  }
]
