{
  "n": "V. G. Wilcox",
  "c": "Maoists",
  "d": "Marxist thinker and theorist in the tradition of maoists.",
  "b": "https://www.marxists.org/reference/archive/",
  "i": "https://upload.wikimedia.org/wikipedia/commons/1/15/Wilcox%2C_Charles_S.%2C_1892-1904_%28President%2C_The_Automobile_Supply_Co.%2C_Chicago%2C_Illinois%29_%28ANS_Chapman_brothers_business_correspondence%29_%28IA_wilcoxcharless1800wilc%29.pdf",
  "t": "https://upload.wikimedia.org/wikipedia/commons/thumb/1/15/Wilcox%2C_Charles_S.%2C_1892-1904_%28President%2C_The_Automobile_Supply_Co.%2C_Chicago%2C_Illinois%29_%28ANS_Chapman_brothers_business_correspondence%29_%28IA_wilcoxcharless1800wilc%29.pdf/page1-200px-thumbnail.pdf.jpg",
  "w": 2,
  "subjects": [
    {
      "name": "General",
      "count": 2
    }
  ],
  "s": "v. g. wilcox maoists marxist thinker and theorist in the tradition of maoists. general"
}
