[
  {
    "n": "A I Meshcheryakov",
    "c": "Soviet Marxism",
    "d": "Marxist thinker and theorist in the tradition of soviet marxism.",
    "b": "https://www.marxists.org/reference/archive/",
    "i": "https://upload.wikimedia.org/wikipedia/commons/6/6a/Grave_of_Meshcheryakov_and_Mashkovtsev_%282021-08-26%29_01.jpg",
    "t": "https://upload.wikimedia.org/wikipedia/commons/thumb/8/88/Grave_of_Meshcheryakov_and_Mashkovtsev_%282021-08-26%29_05.jpg/250px-Grave_of_Meshcheryakov_and_Mashkovtsev_%282021-08-26%29_05.jpg",
    "w": 2
  },
  {
    "n": "Alexander Luria",
    "c": "Soviet Marxism",
    "d": "Marxist thinker and theorist in the tradition of soviet marxism.",
    "b": "https://www.marxists.org/reference/archive/",
    "i": "https://upload.wikimedia.org/wikipedia/commons/6/67/Alexander_Luria.jpg",
    "t": "https://upload.wikimedia.org/wikipedia/commons/thumb/6/67/Alexander_Luria.jpg/250px-Alexander_Luria.jpg",
    "w": 0
  },
  {
    "n": "Alexei Leont'ev",
    "c": "Soviet Marxism",
    "d": "Marxist thinker and theorist in the tradition of soviet marxism.",
    "b": "https://www.marxists.org/reference/archive/",
    "i": "",
    "t": "",
    "w": 9
  },
  {
    "n": "Daniil El'konin",
    "c": "Soviet Marxism",
    "d": "Marxist thinker and theorist in the tradition of soviet marxism.",
    "b": "https://www.marxists.org/reference/archive/",
    "i": "",
    "t": "",
    "w": 3
  },
  {
    "n": "Evald Ilyenkov",
    "c": "Soviet Marxism",
    "d": "Marxist thinker and theorist in the tradition of soviet marxism.",
    "b": "https://www.marxists.org/reference/archive/",
    "i": "https://upload.wikimedia.org/wikipedia/commons/a/a4/Evald_Ilyenkov.jpg",
    "t": "https://upload.wikimedia.org/wikipedia/commons/thumb/a/a4/Evald_Ilyenkov.jpg/250px-Evald_Ilyenkov.jpg",
    "w": 13
  },
  {
    "n": "Evgeny Pashukanis",
    "c": "Soviet Marxism",
    "d": "Marxist thinker and theorist in the tradition of soviet marxism.",
    "b": "https://www.marxists.org/reference/archive/",
    "i": "https://upload.wikimedia.org/wikipedia/commons/7/7d/%D0%95%D0%B2%D0%B3%D0%B5%D0%BD%D0%B8%D0%B9_%D0%9F%D0%B0%D1%88%D1%83%D0%BA%D0%B0%D0%BD%D0%B8%D1%81.jpg",
    "t": "https://upload.wikimedia.org/wikipedia/commons/thumb/7/7d/%D0%95%D0%B2%D0%B3%D0%B5%D0%BD%D0%B8%D0%B9_%D0%9F%D0%B0%D1%88%D1%83%D0%BA%D0%B0%D0%BD%D0%B8%D1%81.jpg/250px-%D0%95%D0%B2%D0%B3%D0%B5%D0%BD%D0%B8%D0%B9_%D0%9F%D0%B0%D1%88%D1%83%D0%BA%D0%B0%D0%BD%D0%B8%D1%81.jpg",
    "w": 10
  },
  {
    "n": "Feliks Mikhailov",
    "c": "Soviet Marxism",
    "d": "Marxist thinker and theorist in the tradition of soviet marxism.",
    "b": "https://www.marxists.org/reference/archive/",
    "i": "https://upload.wikimedia.org/wikipedia/commons/0/0d/Pol%C3%ADtica_Interna_do_Uruguai._Medidas_de_Seguran%C3%A7a%2C_Arquivo_Nacional_%28BR_DFANBSB_IE.0.0.3_%2810-12%29%29.pdf",
    "t": "https://upload.wikimedia.org/wikipedia/commons/thumb/0/0d/Pol%C3%ADtica_Interna_do_Uruguai._Medidas_de_Seguran%C3%A7a%2C_Arquivo_Nacional_%28BR_DFANBSB_IE.0.0.3_%2810-12%29%29.pdf/page1-200px-Pol%C3%ADtica_Interna_do_Uruguai._Medidas_de_Seguran%C3%A7a%2C_Arquivo_Nacional_%28BR_DFANBSB_IE.0.0.3_%2810-12%29%29.pdf.jpg",
    "w": 4
  },
  {
    "n": "Lev Vygotsky",
    "c": "Soviet Marxism",
    "d": "Marxist thinker and theorist in the tradition of soviet marxism.",
    "b": "https://www.marxists.org/reference/archive/",
    "i": "https://upload.wikimedia.org/wikipedia/commons/6/67/Lev-Semyonovich-Vygotsky-1896-1934.jpg",
    "t": "https://upload.wikimedia.org/wikipedia/commons/thumb/6/67/Lev-Semyonovich-Vygotsky-1896-1934.jpg/250px-Lev-Semyonovich-Vygotsky-1896-1934.jpg",
    "w": 31
  },
  {
    "n": "V A Lektorsky",
    "c": "Soviet Marxism",
    "d": "Marxist thinker and theorist in the tradition of soviet marxism.",
    "b": "https://www.marxists.org/reference/archive/",
    "i": "https://upload.wikimedia.org/wikipedia/commons/1/11/Kl%C3%A1ra_Joklov%C3%A1_-_Wikimedia_%C4%8CR_v_roce_2019_a_d%C3%A1le_-_Wikikonference_2019.pdf",
    "t": "https://upload.wikimedia.org/wikipedia/commons/thumb/1/11/Kl%C3%A1ra_Joklov%C3%A1_-_Wikimedia_%C4%8CR_v_roce_2019_a_d%C3%A1le_-_Wikikonference_2019.pdf/page1-200px-Kl%C3%A1ra_Joklov%C3%A1_-_Wikimedia_%C4%8CR_v_roce_2019_a_d%C3%A1le_-_Wikikonference_2019.pdf.jpg",
    "w": 1
  },
  {
    "n": "Valentin Voloshinov",
    "c": "Soviet Marxism",
    "d": "Marxist thinker and theorist in the tradition of soviet marxism.",
    "b": "https://www.marxists.org/reference/archive/",
    "i": "https://upload.wikimedia.org/wikipedia/commons/c/cc/Circulo_de_bajtin_1924.JPG",
    "t": "https://upload.wikimedia.org/wikipedia/commons/thumb/c/cc/Circulo_de_bajtin_1924.JPG/250px-Circulo_de_bajtin_1924.JPG",
    "w": 3
  }
]